vpnium/__init__.py
vpnium/vpnium.py
vpnium-1.0.1.dist-info/LICENSE
vpnium-1.0.1.dist-info/METADATA
vpnium-1.0.1.dist-info/WHEEL
vpnium-1.0.1.dist-info/top_level.txt
vpnium-1.0.1.dist-info/RECORD
