Metadata-Version: 2.1
Name: vpnium
Version: 1.0.1
Summary: Python library for managing a VPN extension for Chrome WebDriver
Home-page: https://github.com/d3kxrma/vpnium
Author: dekxrma
Author-email: qqdjnuxez@gmail.com
License: MIT
Project-URL: Source, https://github.com/d3kxrma/vpnium
Keywords: python,selenium,vpn,proxy
Classifier: Development Status :: 5 - Production/Stable
Classifier: Intended Audience :: Developers
Classifier: Operating System :: Microsoft :: Windows :: Windows 10
Classifier: License :: OSI Approved :: MIT License
Classifier: Programming Language :: Python :: 3
License-File: LICENSE
Requires-Dist: requests
Requires-Dist: chrome-version
Requires-Dist: selenium
